dbrepos/__init__.py
dbrepos/core/__init__.py
dbrepos/core/abstract.py
dbrepos/core/exceptions.py
dbrepos/core/types.py
dbrepos/decorators.py
dbrepos/django/__init__.py
dbrepos/django/filters.py
dbrepos/django/repo.py
dbrepos/shortcuts.py
dbrepos/sqlalchemy/__init__.py
dbrepos/sqlalchemy/filters.py
dbrepos/sqlalchemy/repo.py
dbrepos-0.1.0.dist-info/LICENSE
dbrepos-0.1.0.dist-info/METADATA
dbrepos-0.1.0.dist-info/WHEEL
dbrepos-0.1.0.dist-info/RECORD
