Metadata-Version: 2.3
Name: dbrepos
Version: 0.1.0
Summary: Repository Pattern Implementation for ORM's
License: MIT
Author: Matvey Ivanov
Author-email: cool.matvey250301@gmail.com
Requires-Python: >=3.11
Classifier: Programming Language :: Python :: 3
Classifier: Operating System :: OS Independent
Classifier: License :: OSI Approved :: MIT License
Project-URL: Homepage, https://github.com/MatveyIvanov/dbrepos
Project-URL: Issues, https://github.com/MatveyIvanov/dbrepos/issues
